marlin_cli/api/archetypes.py
marlin_cli/api/modules.py
marlin_cli/commands/__init__.py
marlin_cli/commands/docs.py
marlin_cli/commands/init.py
marlin_cli/commands/install.py
marlin_cli/commands/list.py
marlin_cli/constants.py
marlin_cli/marlin.py
marlin_cli/util/cft_merge.py
marlin_cli/util/json_merge.py
marlin_cli/util/yaml_merge.py
marlin_cli-0.0.16.dist-info/METADATA
marlin_cli-0.0.16.dist-info/WHEEL
marlin_cli-0.0.16.dist-info/entry_points.txt
marlin_cli-0.0.16.dist-info/RECORD
