Metadata-Version: 2.1
Name: marlin-cli
Version: 0.0.16
Summary: 
Author: George Cooper
Author-email: george@marlincode.com
Requires-Python: ==3.11.1
Classifier: Programming Language :: Python :: 3
Requires-Dist: cfn-flip (>=1.3.0,<2.0.0)
Requires-Dist: click (>=8.1.3,<9.0.0)
Requires-Dist: gitpython (>=3.1.30,<4.0.0)
Requires-Dist: pre-commit (>=3.0.4,<4.0.0)
Requires-Dist: python-dotenv (>=0.21.1,<0.22.0)
Requires-Dist: requests (>=2.28.2,<3.0.0)
